umodl/__init__.py
umodl/runumodl.py
umodl/umodl.exe
umodl-0.0.28.dist-info/METADATA
umodl-0.0.28.dist-info/WHEEL
umodl-0.0.28.dist-info/licenses/LICENSE
umodl-0.0.28.dist-info/RECORD
