Metadata-Version: 2.4
Name: umodl
Version: 0.0.28
Summary: A 'subprocess.run' wrapper around the umodl program
Maintainer-Email: The Khiops Team <khiops.team@orange.com>
License-Expression: BSD-3-Clause-Clear
License-File: LICENSE
Project-URL: source, https://github.com/UData-Orange/umodl.git
Requires-Python: >=3.9
